qubolepystream/__init__.py
qubolepystream/connector.py
qubolepystream-0.8.0.dist-info/METADATA
qubolepystream-0.8.0.dist-info/WHEEL
qubolepystream-0.8.0.dist-info/top_level.txt
qubolepystream-0.8.0.dist-info/RECORD
