Metadata-Version: 2.1
Name: qubolepystream
Version: 0.8.0
Summary: Simple and easy to use Qubole connector
Home-page: https://github.com/achilleasatha/PyQubole
Author: Achilleas Athanasiou Fragkoulis
Author-email: achilleasatha@gmail.com
License: MIT
Platform: UNKNOWN
Requires-Dist: qds-sdk
